mini_expectations/__init__.py
mini_expectations/core.py
mini_expectations/py.typed
mini_expectations-0.1.1.dist-info/licenses/LICENSE
mini_expectations-0.1.1.dist-info/METADATA
mini_expectations-0.1.1.dist-info/WHEEL
mini_expectations-0.1.1.dist-info/top_level.txt
mini_expectations-0.1.1.dist-info/RECORD
