Metadata-Version: 2.4
Name: mini_expectations
Version: 0.1.1
Summary: A tiny, code-first data quality expectations library for pandas DataFrames.
Author-email: Sriram Kumar <sriramkumar0109@gmail.com>
License: MIT
Project-URL: Source, https://github.com/batteringram-dev/mini-expectations
Keywords: data-quality,pandas,testing,expectations
Classifier: Programming Language :: Python :: 3
Classifier: Programming Language :: Python :: 3 :: Only
Classifier: License :: OSI Approved :: MIT License
Classifier: Intended Audience :: Developers
Classifier: Topic :: Software Development :: Testing
Requires-Python: >=3.8
License-File: LICENSE
Requires-Dist: pandas>=1.0
Dynamic: license-file
